opensurfacesim/__init__.py
opensurfacesim/__main__.py
opensurfacesim/main.py
opensurfacesim/plot.py
opensurfacesim/threshold.py
opensurfacesim/codes/__init__.py
opensurfacesim/codes/_icons.py
opensurfacesim/codes/elements.py
opensurfacesim/codes/_template/__init__.py
opensurfacesim/codes/_template/plot.py
opensurfacesim/codes/_template/sim.py
opensurfacesim/codes/planar/__init__.py
opensurfacesim/codes/planar/plot.py
opensurfacesim/codes/planar/sim.py
opensurfacesim/codes/rotated/__init__.py
opensurfacesim/codes/toric/__init__.py
opensurfacesim/codes/toric/plot.py
opensurfacesim/codes/toric/sim.py
opensurfacesim/decoders/__init__.py
opensurfacesim/decoders/_template.py
opensurfacesim/decoders/mwpm/__init__.py
opensurfacesim/decoders/mwpm/plot.py
opensurfacesim/decoders/mwpm/sim.py
opensurfacesim/decoders/ufns/__init__.py
opensurfacesim/decoders/ufns/elements.py
opensurfacesim/decoders/ufns/plot.py
opensurfacesim/decoders/ufns/sim.py
opensurfacesim/decoders/unionfind/__init__.py
opensurfacesim/decoders/unionfind/elements.py
opensurfacesim/decoders/unionfind/plot.py
opensurfacesim/decoders/unionfind/sim.py
opensurfacesim/errors/__init__.py
opensurfacesim/errors/_icons.py
opensurfacesim/errors/_template.py
opensurfacesim/errors/erasure.py
opensurfacesim/errors/pauli.py
qsurface/__init__.py
qsurface/__main__.py
qsurface/main.py
qsurface/plot.py
qsurface/threshold.py
qsurface/codes/__init__.py
qsurface/codes/_icons.py
qsurface/codes/elements.py
qsurface/codes/_template/__init__.py
qsurface/codes/_template/plot.py
qsurface/codes/_template/sim.py
qsurface/codes/planar/__init__.py
qsurface/codes/planar/plot.py
qsurface/codes/planar/sim.py
qsurface/codes/rotated/__init__.py
qsurface/codes/toric/__init__.py
qsurface/codes/toric/plot.py
qsurface/codes/toric/sim.py
qsurface/decoders/__init__.py
qsurface/decoders/_template.py
qsurface/decoders/decoders.ini
qsurface/decoders/mwpm/__init__.py
qsurface/decoders/mwpm/plot.py
qsurface/decoders/mwpm/sim.py
qsurface-0.1.5.dist-info/LICENSE
qsurface-0.1.5.dist-info/METADATA
qsurface-0.1.5.dist-info/WHEEL
qsurface-0.1.5.dist-info/entry_points.txt
qsurface-0.1.5.dist-info/top_level.txt
qsurface-0.1.5.dist-info/RECORD
