Metadata-Version: 2.1
Name: qsurface
Version: 0.1.5
Summary: Open library from surface code simulations and visualizations
Home-page: https://github.com/watermarkhu/qsurface
Author: Mark Shui Hu
Author-email: watermarkhu@gmail.com
License: BSD-3
Project-URL: Documentation, https://qsurface.readthedocs.io/en/latest/
Platform: UNKNOWN
Classifier: Development Status :: 3 - Alpha
Classifier: License :: OSI Approved :: BSD License
Classifier: Programming Language :: Python :: 3.7
Classifier: Topic :: Scientific/Engineering :: Physics
Requires-Python: >3.7.0
